README.md
setup.py
zelda/__init__.py
zelda/__main__.py
zelda/debug.py
zelda/version.py
zelda.egg-info/PKG-INFO
zelda.egg-info/SOURCES.txt
zelda.egg-info/dependency_links.txt
zelda.egg-info/entry_points.txt
zelda.egg-info/requires.txt
zelda.egg-info/top_level.txt