Metadata-Version: 1.2
Name: zelda
Version: 0.0.1rc1
Summary: an nlp training framework base tf2.0
Home-page: https://github.com/bo-ke/zelda
Author: kebo
Author-email: kebo0912@outlook.com
License: UNKNOWN
Platform: UNKNOWN
Requires-Python: >=3.6.1
